{
    "ALT-020.pdf": {
        "creation_time": "2024-11-20 02:19:49"
    },
    "HFV-001.pdf": {
        "creation_time": "2024-11-20 02:19:49"
    },
    "IAI-003.pdf": {
        "creation_time": "2024-11-20 08:41:19"
    },
    "IXA-003.pdf": {
        "creation_time": "2024-11-20 08:46:00"
    },
    "IXAP-003.pdf": {
        "creation_time": "2024-11-20 08:52:04"
    },
    "jmv21451.pdf": {
        "creation_time": "2024-11-20 08:53:59"
    },
    "REW-013PP.pdf": {
        "creation_time": "2024-11-20 08:56:09"
    },
    "VSN-400.pdf": {
        "creation_time": "2024-11-20 09:21:08"
    }
}